Metadata-Version: 1.0
Name: pafx
Version: 0.1.0
Summary: Pixel Art effects
Home-page: http://github.com/agateau/pafx
Author: Aurélien Gâteau
Author-email: mail@agateau.com
License: Apache 2.0
Platform: any
